{
 "repo": "apps-fab/exercism-app",
 "stars": 11,
 "categories": [
  "Education"
 ],
 "sha": "3ceb552c1b2eaed8c60e27771f84773aedbd1d3f",
 "platform": "macos",
 "ipad_idioms": [
  "NavigationSplitView"
 ],
 "author_authority": 1147,
 "contributor_count": 3,
 "top_contributors": [
  {
   "login": "angiemugo",
   "score": 30,
   "contributions": 91
  },
  {
   "login": "cedricbahirwe",
   "score": 3061,
   "contributions": 63
  },
  {
   "login": "savekirk",
   "score": 31,
   "contributions": 14
  }
 ],
 "loc": 6982,
 "custom_components": 126,
 "imports": [
  "AppKit",
  "CodeEditor",
  "Combine",
  "ExercismSwift",
  "Exercode",
  "Foundation",
  "KeychainAccess",
  "MarkdownUI",
  "SDWebImage",
  "SDWebImageSVGCoder",
  "SDWebImageSwiftUI",
  "Settings",
  "Splash",
  "SwiftUI",
  "XCTest"
 ],
 "min_ios_inferred": "26",
 "deprecated_apis_used": [
  "Alert",
  "colorMultiply",
  "disableAutocorrection",
  "edgesIgnoringSafeArea",
  "foregroundColor",
  "tabItem"
 ],
 "unique": {
  "modifiers": [
   "accessibilityAddTraits",
   "accessibilityHidden",
   "accessibilityHint",
   "accessibilityLabel",
   "accessibilityValue",
   "alert",
   "animation",
   "aspectRatio",
   "background",
   "bold",
   "border",
   "brightness",
   "buttonStyle",
   "clipShape",
   "colorInvert",
   "colorMultiply",
   "commands",
   "contentShape",
   "controlSize",
   "cornerRadius",
   "defaultSize",
   "disableAutocorrection",
   "disabled",
   "drawingGroup",
   "edgesIgnoringSafeArea",
   "environment",
   "environmentObject",
   "fixedSize",
   "focused",
   "font",
   "foregroundColor",
   "foregroundStyle",
   "frame",
   "gaugeStyle",
   "id",
   "imageScale",
   "interactiveDismissDisabled",
   "keyboardShortcut",
   "labelStyle",
   "labelsHidden",
   "lineLimit",
   "listRowSeparator",
   "listStyle",
   "minimumScaleFactor",
   "modifier",
   "multilineTextAlignment",
   "navigationBarBackButtonHidden",
   "navigationDestination",
   "navigationTitle",
   "onAppear",
   "onChange",
   "onHover",
   "onPreferenceChange",
   "onReceive",
   "onSubmit",
   "onTapGesture",
   "opacity",
   "padding",
   "pickerStyle",
   "popover",
   "preference",
   "progressViewStyle",
   "renderingMode",
   "resizable",
   "safeAreaInset",
   "scaleEffect",
   "scaledToFit",
   "shadow",
   "sheet",
   "strokeBorder",
   "symbolEffect",
   "symbolRenderingMode",
   "tabItem",
   "tag",
   "task",
   "textCase",
   "textFieldStyle",
   "tint",
   "toolbar",
   "weight"
  ],
  "types": [
   "Alert",
   "Binding",
   "Button",
   "Color",
   "CommandGroup",
   "DisclosureGroup",
   "Divider",
   "EmptyView",
   "Environment",
   "Font",
   "ForEach",
   "Gauge",
   "GeometryReader",
   "Gradient",
   "GridItem",
   "Group",
   "HStack",
   "Image",
   "Label",
   "LazyVGrid",
   "LinearGradient",
   "List",
   "Menu",
   "NavigationSplitView",
   "NavigationStack",
   "Picker",
   "ProgressView",
   "Rectangle",
   "RoundedRectangle",
   "ScrollView",
   "SidebarCommands",
   "Spacer",
   "StateObject",
   "Text",
   "TextField",
   "ToolbarItem",
   "VStack",
   "ZStack"
  ],
  "valueBuilders": [
   "bottomLeading",
   "callout",
   "headline",
   "linear",
   "medium",
   "regular",
   "semibold",
   "subheadline",
   "system",
   "title2",
   "title3"
  ],
  "macros": [
   "Preview"
  ],
  "styleValues": [
   "accessoryLinearCapacity",
   "automatic",
   "black",
   "blue",
   "bottom",
   "cancel",
   "center",
   "circular",
   "clear",
   "dark",
   "default",
   "fill",
   "foreground",
   "gray",
   "green",
   "hard",
   "largeTitle",
   "leading",
   "light",
   "orange",
   "plain",
   "primary",
   "primaryAction",
   "principal",
   "red",
   "secondary",
   "single",
   "thickMaterial",
   "title",
   "titleAndIcon",
   "top",
   "trailing",
   "white",
   "yellow"
  ],
  "propertyWrappers": [
   "AppStorage",
   "Binding",
   "Environment",
   "EnvironmentObject",
   "FocusState",
   "ObservedObject",
   "SceneStorage",
   "State",
   "StateObject"
  ],
  "environmentKeys": [
   "colorScheme",
   "dismiss",
   "openURL",
   "openWindow"
  ]
 },
 "counts": {
  "modifiers": 80,
  "types": 38,
  "valueBuilders": 11,
  "macros": 1,
  "styleValues": 34,
  "propertyWrappers": 9,
  "environmentKeys": 4
 },
 "total_unique_apis": 177
}