{
 "repo": "wikimedia/wikipedia-ios",
 "stars": 3398,
 "categories": [
  "Official"
 ],
 "sha": "1fd00245870a9a7fb923e49d064f7b9b7160d77f",
 "platform": "ios",
 "ipad_idioms": [
  "ViewThatFits",
  "containerRelativeFrame"
 ],
 "author_authority": 1154,
 "contributor_count": 3,
 "top_contributors": [
  {
   "login": "joewalsh",
   "score": 1,
   "contributions": 11650
  },
  {
   "login": "tonisevener",
   "score": 3419,
   "contributions": 7489
  },
  {
   "login": "montehurd",
   "score": 5227,
   "contributions": 5426
  }
 ],
 "loc": 190192,
 "custom_components": 486,
 "imports": [
  "AVFoundation",
  "AVKit",
  "BackgroundTasks",
  "Charts",
  "CocoaLumberjackSwift",
  "Combine",
  "Contacts",
  "CoreData",
  "CoreGraphics",
  "CoreLocation",
  "CoreSpotlight",
  "Foundation",
  "HCaptcha",
  "LinkPresentation",
  "MapKit",
  "MessageUI",
  "MobileCoreServices",
  "NotificationCenter",
  "PackageDescription",
  "PassKit",
  "SDWebImage",
  "SwiftUI",
  "SystemConfiguration",
  "Testing",
  "TipKit",
  "UIKit",
  "UserNotifications",
  "WMF",
  "WMFComponents",
  "WMFData",
  "WMFDataMocks",
  "WMFNativeLocalizations",
  "WMFTestKitchen",
  "WMFTranslateWikiLocalizations",
  "WebKit",
  "WidgetKit",
  "Wikipedia",
  "XCTest",
  "_PassKit_SwiftUI",
  "os"
 ],
 "min_ios_inferred": "26",
 "deprecated_apis_used": [
  "NavigationView",
  "accentColor",
  "edgesIgnoringSafeArea",
  "foregroundColor",
  "navigationViewStyle",
  "sizeCategory",
  "stack"
 ],
 "unique": {
  "modifiers": [
   "accentColor",
   "accessibilityAction",
   "accessibilityActions",
   "accessibilityAddTraits",
   "accessibilityFocused",
   "accessibilityHidden",
   "accessibilityHint",
   "accessibilityIdentifier",
   "accessibilityLabel",
   "accessibilityRemoveTraits",
   "accessibilityValue",
   "alert",
   "alignmentGuide",
   "allowsHitTesting",
   "animation",
   "aspectRatio",
   "background",
   "blendMode",
   "buttonStyle",
   "chartXAxis",
   "chartYAxis",
   "clipShape",
   "clipped",
   "compositingGroup",
   "containerBackground",
   "containerRelativeFrame",
   "contentMargins",
   "contentShape",
   "contextMenu",
   "cornerRadius",
   "datePickerStyle",
   "disabled",
   "dynamicTypeSize",
   "edgesIgnoringSafeArea",
   "environment",
   "environmentObject",
   "fixedSize",
   "flipsForRightToLeftLayoutDirection",
   "focusEffectDisabled",
   "focusable",
   "focused",
   "font",
   "foregroundColor",
   "foregroundStyle",
   "frame",
   "glassEffect",
   "glassEffectID",
   "highPriorityGesture",
   "id",
   "ignoresSafeArea",
   "keyboardType",
   "labelStyle",
   "labelsHidden",
   "layoutPriority",
   "lineLimit",
   "lineSpacing",
   "listRowBackground",
   "listRowInsets",
   "listRowSeparator",
   "listRowSeparatorTint",
   "listSectionSeparator",
   "listSectionSpacing",
   "listStyle",
   "mask",
   "minimumScaleFactor",
   "modifier",
   "monospacedDigit",
   "multilineTextAlignment",
   "navigationBarTitleDisplayMode",
   "navigationTitle",
   "navigationViewStyle",
   "offset",
   "onAppear",
   "onChange",
   "onDisappear",
   "onEnded",
   "onPreferenceChange",
   "onReceive",
   "onTapGesture",
   "opacity",
   "overlay",
   "padding",
   "pickerStyle",
   "preference",
   "previewContext",
   "previewDisplayName",
   "progressViewStyle",
   "refreshable",
   "renderingMode",
   "resizable",
   "scale",
   "scaleEffect",
   "scaledToFill",
   "scaledToFit",
   "scrollBounceBehavior",
   "scrollContentBackground",
   "scrollIndicatorsFlash",
   "shadow",
   "strokeBorder",
   "submitLabel",
   "swipeActions",
   "symbolRenderingMode",
   "tabViewStyle",
   "tag",
   "task",
   "textCase",
   "tint",
   "toggleStyle",
   "toolbar",
   "truncationMode",
   "weight",
   "widgetURL",
   "zIndex"
  ],
  "types": [
   "AnyView",
   "AsyncImage",
   "Binding",
   "BorderlessButtonStyle",
   "Button",
   "Capsule",
   "Chart",
   "Circle",
   "CircularProgressViewStyle",
   "Color",
   "DatePicker",
   "Divider",
   "EdgeInsets",
   "EmptyView",
   "Font",
   "ForEach",
   "Form",
   "GeometryReader",
   "GlassEffectContainer",
   "Gradient",
   "GridItem",
   "Group",
   "GroupedListStyle",
   "HStack",
   "Image",
   "ImageRenderer",
   "InsetGroupedListStyle",
   "Label",
   "LazyVGrid",
   "LazyVStack",
   "LineMark",
   "LinearGradient",
   "Link",
   "List",
   "Menu",
   "NavigationView",
   "OpenURLAction",
   "Path",
   "Picker",
   "ProgressView",
   "Rectangle",
   "RoundedRectangle",
   "ScrollView",
   "ScrollViewReader",
   "Section",
   "Spacer",
   "StateObject",
   "StaticConfiguration",
   "Stepper",
   "StrokeStyle",
   "SwitchToggleStyle",
   "TabView",
   "TapGesture",
   "Text",
   "TextEditor",
   "TextField",
   "Timeline",
   "TimelineView",
   "Toggle",
   "ToolbarItem",
   "ToolbarItemGroup",
   "UIHostingController",
   "VStack",
   "VerticalAlignment",
   "View",
   "ViewThatFits",
   "WidgetPreviewContext",
   "ZStack"
  ],
  "valueBuilders": [
   "body",
   "bottomLeading",
   "bottomTrailing",
   "callout",
   "caption",
   "caption2",
   "custom",
   "easeIn",
   "easeInOut",
   "easeOut",
   "footnote",
   "headline",
   "medium",
   "push",
   "regular",
   "semibold",
   "spring",
   "subheadline",
   "system",
   "title2",
   "title3",
   "topLeading",
   "topTrailing"
  ],
  "macros": [
   "Preview"
  ],
  "styleValues": [
   "accessoryCircular",
   "automatic",
   "black",
   "blue",
   "bottom",
   "bottomBar",
   "button",
   "cancel",
   "center",
   "circular",
   "clear",
   "compact",
   "dark",
   "date",
   "default",
   "destructive",
   "fill",
   "firstTextBaseline",
   "glass",
   "glassProminent",
   "graphical",
   "gray",
   "green",
   "grouped",
   "hard",
   "iconOnly",
   "identity",
   "inline",
   "insetGrouped",
   "interactive",
   "keyboard",
   "leading",
   "light",
   "linear",
   "link",
   "orange",
   "page",
   "palette",
   "pink",
   "placeholder",
   "plain",
   "primary",
   "purple",
   "regularMaterial",
   "secondary",
   "segmented",
   "single",
   "stack",
   "switch",
   "titleAndIcon",
   "top",
   "topBarLeading",
   "topBarTrailing",
   "trailing",
   "white",
   "yellow"
  ],
  "propertyWrappers": [
   "AccessibilityFocusState",
   "Binding",
   "Environment",
   "EnvironmentObject",
   "FocusState",
   "Namespace",
   "ObservedObject",
   "ScaledMetric",
   "State",
   "StateObject"
  ],
  "environmentKeys": [
   "colorScheme",
   "dismiss",
   "dynamicTypeSize",
   "horizontalSizeClass",
   "layoutDirection",
   "openURL",
   "sizeCategory",
   "verticalSizeClass",
   "widgetFamily"
  ]
 },
 "counts": {
  "modifiers": 113,
  "types": 68,
  "valueBuilders": 23,
  "macros": 1,
  "styleValues": 56,
  "propertyWrappers": 10,
  "environmentKeys": 9
 },
 "total_unique_apis": 280
}